detritalpy/__init__.py
detritalpy/adaptiveKDE.py
detritalpy/detritalFuncs.py
detritalpy-1.2.3.data/scripts/adaptiveKDE.py
detritalpy-1.2.3.data/scripts/detritalFuncs.py
detritalpy-1.2.3.dist-info/LICENSE
detritalpy-1.2.3.dist-info/METADATA
detritalpy-1.2.3.dist-info/WHEEL
detritalpy-1.2.3.dist-info/top_level.txt
detritalpy-1.2.3.dist-info/RECORD
