Metadata-Version: 2.1
Name: detritalpy
Version: 1.2.3
Summary: A Python-based toolset for visualizing and analyzing detrital geo-thermochronologic data
Home-page: https://github.com/grsharman/detritalpy
Author: Glenn Sharman
Author-email: gsharman@uark.edu
License: UNKNOWN
Keywords: detrital,zircon,provenance,stratigraphy,geochronology,thermochronology
Platform: UNKNOWN
Classifier: Programming Language :: Python :: 3
Classifier: Intended Audience :: Science/Research
Classifier: License :: OSI Approved :: Apache Software License
Classifier: Operating System :: OS Independent
Requires-Dist: numpy
Requires-Dist: matplotlib
Requires-Dist: pandas
Requires-Dist: xlrd
Requires-Dist: folium
Requires-Dist: vincent
Requires-Dist: simplekml
Requires-Dist: scipy
Requires-Dist: sklearn
Requires-Dist: statsmodels
Requires-Dist: peakutils
